README.rst
pyproject.toml
setup.py
bin/objbot
bin/objbotc
bin/objbotd
bin/objbots
objbot/__init__.py
objbot.egg-info/PKG-INFO
objbot.egg-info/SOURCES.txt
objbot.egg-info/dependency_links.txt
objbot.egg-info/requires.txt
objbot.egg-info/top_level.txt
objbot.egg-info/zip-safe
objbot/modules/__init__.py
objbot/modules/cmd.py
objbot/modules/err.py
objbot/modules/face.py
objbot/modules/irc.py
objbot/modules/log.py
objbot/modules/mod.py
objbot/modules/rss.py
objbot/modules/tdo.py
objbot/modules/thr.py
objbot/modules/upt.py