Metadata-Version: 2.1
Name: objbot
Version: 104
Summary: objects bot
Author-email: Bart Thate <rssbotd@gmail.com>
License: Public Domain
Project-URL: home, https://pypi.org/project/objbot
Project-URL: bugs, https://github.com/rssbotd/objbot/issues
Project-URL: source, https://github.com/rssbotd/objbot
Classifier: Development Status :: 3 - Alpha
Classifier: License :: Public Domain
Classifier: Operating System :: Unix
Classifier: Programming Language :: Python
Classifier: Topic :: Utilities
Provides-Extra: dev
